{"Mana Ascetic_PSA":{"mainCount":4,"sideCount":0},"Chi Lee of the Underworld_VTM":{"mainCount":3,"sideCount":0},"Ruin Delver_WAY":{"mainCount":3,"sideCount":0},"Hellion Devastator_ALR":{"mainCount":2,"sideCount":0},"Kaalia's Abomination_ALR":{"mainCount":2,"sideCount":0},"Aiel Tazan_ZER":{"mainCount":2,"sideCount":0},"Lucien, the Grifter_VTM":{"mainCount":2,"sideCount":0},"Xiong Mao, the Intrepid_GHQ":{"mainCount":3,"sideCount":0},"Edarna the Everforge_ALR":{"mainCount":1,"sideCount":0},"Pith Wilt_KOD":{"mainCount":4,"sideCount":0},"Whisperwood Exploration_STN":{"mainCount":3,"sideCount":0},"Duress_DOA":{"mainCount":4,"sideCount":0},"Singularity's Grasp_RWR":{"mainCount":0,"sideCount":2},"Tend to the Grove_MS3":{"mainCount":3,"sideCount":0},"Wayfarer's Shrine_IMP":{"mainCount":4,"sideCount":0},"Grim Bastion_KZD":{"mainCount":3,"sideCount":0},"Timber Range_L":{"mainCount":2,"sideCount":0},"Shardstone Rift_L":{"mainCount":1,"sideCount":0},"Forest_AFM":{"mainCount":2,"sideCount":0},"Mountain_AFM":{"mainCount":1,"sideCount":0},"Swamp_AFM":{"mainCount":2,"sideCount":0},"Lumbering Hillock_CAC":{"mainCount":1,"sideCount":0},"Fungal Mire_TOW":{"mainCount":1,"sideCount":0},"Nomad's Township_PFP":{"mainCount":2,"sideCount":0},"Rampant Summit_PFP":{"mainCount":2,"sideCount":0},"Crumbling Precipice_PFP":{"mainCount":2,"sideCount":0},"Seal the Tomb_TWR":{"mainCount":0,"sideCount":3},"Nature's Claim_GHQ":{"mainCount":0,"sideCount":2},"Stand Unassailable_RWR":{"mainCount":0,"sideCount":4},"Prying Inquiry_UNR":{"mainCount":0,"sideCount":3},"Ignition Ritual_CAC":{"mainCount":0,"sideCount":1}}