{"Aryam the Dreamer_DHL":{"mainCount":2,"sideCount":0},"Tranquil Ascetic_IMP":{"mainCount":3,"sideCount":0},"Rhudai Overseer_SOU":{"mainCount":3,"sideCount":0},"Featherfall Ascetic_UNR":{"mainCount":4,"sideCount":0},"Dreamsteel Paladin_MS1":{"mainCount":3,"sideCount":0},"Unbreachable Walls_WAW":{"mainCount":0,"sideCount":1},"Journey's End_WAY":{"mainCount":0,"sideCount":2},"Event Horizon_MON":{"mainCount":0,"sideCount":1},"Ethereal Armor_TOW":{"mainCount":4,"sideCount":0},"Slaffield Workgate_UNR":{"mainCount":2,"sideCount":0},"Golden Touch_VTM":{"mainCount":3,"sideCount":0},"Bulletproof Will_LVS":{"mainCount":3,"sideCount":0},"Skypath Pilgrimage_MS3":{"mainCount":3,"sideCount":0},"Ocean Monastery_L":{"mainCount":2,"sideCount":0},"Plains_AFM":{"mainCount":3,"sideCount":0},"Island_AFM":{"mainCount":3,"sideCount":0},"Zhelid, Planar Academy_WAY":{"mainCount":2,"sideCount":0},"Sea Of Skies Beyond_NVA":{"mainCount":1,"sideCount":0},"Gleaming River_KOD":{"mainCount":3,"sideCount":0},"Vast Savannah_KOD":{"mainCount":3,"sideCount":0},"Sedate Tundra_PFP":{"mainCount":3,"sideCount":0},"Pool of Light_K15":{"mainCount":2,"sideCount":0},"Guiding Light_ATB":{"mainCount":0,"sideCount":2},"Sigil of Radiance_CAC":{"mainCount":0,"sideCount":2},"Temporary Treason_AFM":{"mainCount":0,"sideCount":2},"Seabreen Nullmage_ZER":{"mainCount":0,"sideCount":2},"Jaws of the Sea_STN":{"mainCount":0,"sideCount":3}}