{"Soul's Attendant_LNG":{"mainCount":4,"sideCount":0},"Soul Warden_K15":{"mainCount":4,"sideCount":0},"Stalked Healer_KLC":{"mainCount":4,"sideCount":0},"Keeper of the Sanctum_STN":{"mainCount":4,"sideCount":0},"Parish Paragon_EAU":{"mainCount":4,"sideCount":0},"Servant of Akatosh_WAW":{"mainCount":4,"sideCount":0},"Sun-Sigil Ordainer_ALR":{"mainCount":4,"sideCount":0},"Carnival Yatiri_MS2":{"mainCount":4,"sideCount":0},"Saigura Tam_DYA":{"mainCount":4,"sideCount":0},"Tendrilsnare_ALR":{"mainCount":4,"sideCount":0},"Vast Savannah_KOD":{"mainCount":4,"sideCount":0},"Resplendent Substratum_PFP":{"mainCount":4,"sideCount":0},"Forgotten Steppe_PFP":{"mainCount":4,"sideCount":0},"Forest_AFM":{"mainCount":1,"sideCount":0},"Mountain_AFM":{"mainCount":1,"sideCount":0},"Plains_AFM":{"mainCount":4,"sideCount":0},"Amber Hills_KZD":{"mainCount":1,"sideCount":0},"Sunlit Highland_KZD":{"mainCount":1,"sideCount":0},"Stand Unassailable_RWR":{"mainCount":0,"sideCount":4},"Aiel Tazan_ZER":{"mainCount":0,"sideCount":2},"Burning Revelations_EAU":{"mainCount":0,"sideCount":3},"Imperial Claim_SOU":{"mainCount":0,"sideCount":3},"Bahum, the Warden_VTM":{"mainCount":0,"sideCount":3}}