{"Profane Emissary_ALR":{"mainCount":4,"sideCount":0},"Knight of Order_WAW":{"mainCount":4,"sideCount":0},"Kaalia, Sky's End_ALR":{"mainCount":3,"sideCount":0},"Jejun, Dark Hunter_DHL":{"mainCount":1,"sideCount":0},"Cypress, the Wayfarer_EAU":{"mainCount":4,"sideCount":0},"Helena, the Awakener_EAU":{"mainCount":4,"sideCount":0},"Rain Zai, Spiritscale_DHL":{"mainCount":3,"sideCount":0},"Pith Wilt_KOD":{"mainCount":4,"sideCount":0},"Tendrilsnare_ALR":{"mainCount":2,"sideCount":0},"Golden Touch_VTM":{"mainCount":4,"sideCount":0},"Expedition Post_WAY":{"mainCount":4,"sideCount":0},"Polyp Pools_WAY":{"mainCount":4,"sideCount":0},"Amber Hills_KZD":{"mainCount":4,"sideCount":0},"Barren Desolation_L":{"mainCount":1,"sideCount":0},"Grim Bastion_KZD":{"mainCount":1,"sideCount":0},"Burial Grounds_WAW":{"mainCount":3,"sideCount":0},"Resplendent Substratum_PFP":{"mainCount":3,"sideCount":0},"Nomad's Township_PFP":{"mainCount":1,"sideCount":0},"Arctic Mine_PFP":{"mainCount":1,"sideCount":0},"Plains_AFM":{"mainCount":2,"sideCount":0},"Forest_AFM":{"mainCount":1,"sideCount":0},"Swamp_AFM":{"mainCount":2,"sideCount":0},"Face the Dawn_CAC":{"mainCount":0,"sideCount":4},"Bahum, the Warden_VTM":{"mainCount":0,"sideCount":3},"Deem Unworthy_WAW":{"mainCount":0,"sideCount":3},"Out-of-Body Experience_LVS":{"mainCount":0,"sideCount":3},"Imperial Claim_SOU":{"mainCount":0,"sideCount":2}}