{"Thalmor Agent":{"mainCount":3,"sideCount":0},"Elvish Opportunist":{"mainCount":4,"sideCount":0},"Dovon, Verdant Experimenter":{"mainCount":1,"sideCount":0},"Thalmor Marshal":{"mainCount":3,"sideCount":0},"Bosmer Ambusher":{"mainCount":4,"sideCount":0},"Ancestral Speaker":{"mainCount":2,"sideCount":0},"Wardbane Mystic":{"mainCount":2,"sideCount":0},"Apprentice Summoner":{"mainCount":2,"sideCount":0},"Sentinel of Latter Days":{"mainCount":3,"sideCount":0},"Elndor, Aldmeri Commander":{"mainCount":1,"sideCount":0},"Mawdryk, Endrison Warden":{"mainCount":2,"sideCount":0},"Romana the Ambassador":{"mainCount":2,"sideCount":0},"Veil's Recovery":{"mainCount":3,"sideCount":0},"Lowered Guard":{"mainCount":2,"sideCount":0},"Turn to Gold":{"mainCount":2,"sideCount":0},"Nomad's Township":{"mainCount":4,"sideCount":0},"Fungal Mire":{"mainCount":4,"sideCount":0},"Forest":{"mainCount":9,"sideCount":0},"Swamp":{"mainCount":7,"sideCount":0},"Singularity's Grasp":{"mainCount":0,"sideCount":4},"Seal the Tomb":{"mainCount":0,"sideCount":3},"Nature's Claim":{"mainCount":0,"sideCount":4},"Titan Snare":{"mainCount":0,"sideCount":2},"The Moon Rises":{"mainCount":0,"sideCount":2}}