{"Dovon, Verdant Experimenter_DOA":{"mainCount":2,"sideCount":0},"Declan, Wayward Squire_TWR":{"mainCount":3,"sideCount":0},"Mana Ascetic_PSA":{"mainCount":4,"sideCount":0},"Tsang Jin, Master of the Jade Sea_PSA":{"mainCount":3,"sideCount":0},"Virida the Forgotten One_DYA":{"mainCount":4,"sideCount":0},"Leyran Alpha_MS2":{"mainCount":4,"sideCount":0},"Pith Wilt_KOD":{"mainCount":4,"sideCount":0},"Strangulate_ATB":{"mainCount":3,"sideCount":0},"Dark Bargain_ZER":{"mainCount":4,"sideCount":0},"Shizen, the Thousand Steps_TOJ":{"mainCount":3,"sideCount":0},"Chamber of Reflections_WAY":{"mainCount":4,"sideCount":0},"Ravaged Monument_ATB":{"mainCount":1,"sideCount":0},"Barren Boneyard_ATB":{"mainCount":1,"sideCount":0},"Sunset Sands_LNG":{"mainCount":4,"sideCount":0},"Flourishing Dunes_ATB":{"mainCount":2,"sideCount":0},"Stygian Dunes_ATB":{"mainCount":2,"sideCount":0},"Nereba, Sandchoked Archives_WAY":{"mainCount":1,"sideCount":0},"Unending Sands_LNG":{"mainCount":4,"sideCount":0},"Forest_AFM":{"mainCount":5,"sideCount":0},"Swamp_AFM":{"mainCount":2,"sideCount":0},"Howling Alpha_WAW":{"mainCount":0,"sideCount":3},"Ser Malcomn_TWR":{"mainCount":0,"sideCount":2},"Vibrant Rapture_EAU":{"mainCount":0,"sideCount":2},"Conjuring of Locusts_CAC":{"mainCount":0,"sideCount":2},"Memento Mori_101":{"mainCount":0,"sideCount":3},"Stolen Secrets_TOJ":{"mainCount":0,"sideCount":3}}