{"Union Rail Strikebreaker_RWR":{"mainCount":4,"sideCount":0},"Centered Acolyte_GHQ":{"mainCount":4,"sideCount":0},"Platinum Colossus_VTM":{"mainCount":2,"sideCount":0},"Self Replication_DOA":{"mainCount":4,"sideCount":0},"Spell Stutter_LNG":{"mainCount":4,"sideCount":0},"Sunken Ambitions_TWR":{"mainCount":0,"sideCount":2},"Opt_DOA":{"mainCount":4,"sideCount":0},"Reconsider_DOA":{"mainCount":2,"sideCount":0},"Consult the Dewdrops_GNJ":{"mainCount":2,"sideCount":0},"Stormwake_PSA":{"mainCount":4,"sideCount":0},"Reinvent_DOA":{"mainCount":4,"sideCount":0},"Northern Express Line_RWR":{"mainCount":4,"sideCount":0},"Lumenbay Flyer Line_RWR":{"mainCount":4,"sideCount":0},"Brine Fleet Bay_WAY":{"mainCount":2,"sideCount":0},"Canyon Falls_LNG":{"mainCount":4,"sideCount":0},"Murky Isle_XPM":{"mainCount":4,"sideCount":0},"Aquatic Refuge_SUR":{"mainCount":4,"sideCount":0},"Frozen Hinterlands_STN":{"mainCount":2,"sideCount":0},"Specialist Saboteur_RWR":{"mainCount":0,"sideCount":1},"Out-of-Body Experience_LVS":{"mainCount":0,"sideCount":4},"Hesitate_XPM":{"mainCount":0,"sideCount":4},"Wheat from Chaff_KLC":{"mainCount":0,"sideCount":4}}