{"Xanigan, the Darkened Cloud_MS2":{"mainCount":2,"sideCount":0},"Iviana, Speaker of Fangs_MS2":{"mainCount":2,"sideCount":0},"Lord Ellison Crain_DSS":{"mainCount":2,"sideCount":0},"Exeunt_VTM":{"mainCount":4,"sideCount":0},"Pierce the Storm_IMP":{"mainCount":3,"sideCount":0},"Sea Cache_TOJ":{"mainCount":4,"sideCount":0},"Crystal Wave_MAC":{"mainCount":4,"sideCount":0},"Descend on the Helpless//Cormoran, Raven Monarch_STN":{"mainCount":2,"sideCount":0},"Unceasing Flames_101":{"mainCount":4,"sideCount":0},"Fair Trial_DSS":{"mainCount":3,"sideCount":0},"Prying Inquiry_UNR":{"mainCount":3,"sideCount":0},"Endless Discoveries_STN":{"mainCount":2,"sideCount":0},"Nereba, Sandchoked Archives_WAY":{"mainCount":1,"sideCount":0},"Back Alley_TGE":{"mainCount":1,"sideCount":0},"Torchlit Shipyard_L":{"mainCount":1,"sideCount":0},"Wayfarer's Shrine_IMP":{"mainCount":4,"sideCount":0},"Swamp_AFM":{"mainCount":1,"sideCount":0},"Mountain_AFM":{"mainCount":1,"sideCount":0},"Island_AFM":{"mainCount":1,"sideCount":0},"Snow-Covered Swamp_DYA":{"mainCount":1,"sideCount":0},"Flooded Depths_KZD":{"mainCount":4,"sideCount":0},"Magmatic Torrent_KZD":{"mainCount":2,"sideCount":0},"Crumbling Precipice_PFP":{"mainCount":1,"sideCount":0},"Monument of Queens_WAY":{"mainCount":1,"sideCount":0},"Anzen, Beyond the Sea_PSA":{"mainCount":1,"sideCount":0},"Murmuring Falls_PFP":{"mainCount":2,"sideCount":0},"Flooded Morass_K15":{"mainCount":2,"sideCount":0},"Crystal Cavern_PFP":{"mainCount":1,"sideCount":0},"Garth of the Chimera_DSS":{"mainCount":0,"sideCount":1},"Seal the Tomb_TWR":{"mainCount":0,"sideCount":3},"Thought Blossom_CAC":{"mainCount":0,"sideCount":4},"Memento Mori_101":{"mainCount":0,"sideCount":2},"Lucien, the Grifter_VTM":{"mainCount":0,"sideCount":2},"Ignition Ritual_CAC":{"mainCount":0,"sideCount":3}}