{"matches":[{"players":[{"id":"221078603926863872","username":"NazSmith","wins":2,"losses":0,"winner":1,"run":1,"list":"/gp_20_07/NazSmith"},{"id":"222555972185358337","username":"TheMafias","wins":0,"losses":2,"winner":0,"run":1,"list":"/gp_20_07/TheMafias"}],"winner":"221078603926863872"},{"players":[{"id":"166685542740787200","username":"FifthDragon","wins":2,"losses":1,"winner":1,"run":1,"list":"/gp_20_07/FifthDragon"},{"id":"380481522416746502","username":"crushcastles23","wins":1,"losses":2,"winner":0,"run":1,"list":"/gp_20_07/crushcastles23"}],"winner":"166685542740787200"},{"players":[{"id":"197714567537754113","username":"Hoop_Thrower","wins":2,"losses":0,"winner":1,"run":1,"list":"/gp_20_07/Hoop_Thrower"},{"id":"353148035594977281","username":"gunnarinator","wins":0,"losses":2,"winner":0,"run":1,"list":"/gp_20_07/gunnarinator"}],"winner":"197714567537754113"},{"players":[{"id":"154993946525696010","username":"HonchkrowDavid","wins":2,"losses":0,"winner":1,"run":1,"list":"/gp_20_07/HonchkrowDavid"},{"id":"256060750492073984","username":"Datacorn","wins":0,"losses":2,"winner":0,"run":1,"list":"/gp_20_07/Datacorn"}],"winner":"154993946525696010"},{"players":[{"id":"186824142299856896","username":"kayiu102","wins":2,"losses":0,"winner":1,"run":1,"list":"/gp_20_07/kayiu102"},{"id":"201750307485515776","username":"augur","wins":0,"losses":2,"winner":0,"run":1,"list":"/gp_20_07/augur"}],"winner":"186824142299856896"},{"players":[{"id":"139184614567575553","username":"CanterburyEgg","wins":2,"losses":1,"winner":1,"run":1,"list":"/gp_20_07/CanterburyEgg"},{"id":"180885469037461504","username":"BluesEclipse","wins":1,"losses":2,"winner":0,"run":1,"list":"/gp_20_07/BluesEclipse"}],"winner":"139184614567575553"},{"players":[{"id":"228286499953704961","username":"CyberChronometer","wins":2,"losses":0,"winner":1,"run":1,"list":"/gp_20_07/CyberChronometer"},{"id":"460867085694795797","username":"Gateways7","wins":0,"losses":2,"winner":0,"run":1,"list":"/gp_20_07/Gateways7"}],"winner":"228286499953704961"},{"players":[{"id":"107957368997834752","username":"ThatDamnPipsqueak","wins":2,"losses":1,"winner":1,"run":1,"list":"/gp_20_07/ThatDamnPipsqueak"},{"id":"326956620535955457","username":"Splitmoon","wins":1,"losses":2,"winner":0,"run":1,"list":"/gp_20_07/Splitmoon"}],"winner":"107957368997834752"},{"players":[{"id":"126785105556537344","username":"HerziQuerzi","wins":2,"losses":0,"winner":1,"run":1,"list":"/gp_20_07/HerziQuerzi"},{"id":"524687574992945163","username":"InfinityChef","wins":0,"losses":2,"winner":0,"run":1,"list":"/gp_20_07/InfinityChef"}],"winner":"126785105556537344"},{"players":[{"id":"326956620535955457","username":"Splitmoon","wins":2,"losses":0,"winner":1,"run":1,"list":"/gp_20_07/Splitmoon"},{"id":"222555972185358337","username":"TheMafias","wins":0,"losses":2,"winner":0,"run":1,"list":"/gp_20_07/TheMafias"}],"winner":"326956620535955457"},{"players":[{"id":"353148035594977281","username":"gunnarinator","wins":2,"losses":0,"winner":1,"run":1,"list":"/gp_20_07/gunnarinator"},{"id":"180885469037461504","username":"BluesEclipse","wins":0,"losses":2,"winner":0,"run":1,"list":"/gp_20_07/BluesEclipse"}],"winner":"353148035594977281"},{"players":[{"id":"460867085694795797","username":"Gateways7","wins":2,"losses":0,"winner":1,"run":1,"list":"/gp_20_07/Gateways7"},{"id":"380481522416746502","username":"crushcastles23","wins":0,"losses":2,"winner":0,"run":1,"list":"/gp_20_07/crushcastles23"}],"winner":"460867085694795797"},{"players":[{"id":"524687574992945163","username":"InfinityChef","wins":2,"losses":0,"winner":1,"run":1,"list":"/gp_20_07/InfinityChef"},{"id":"256060750492073984","username":"Datacorn","wins":0,"losses":2,"winner":0,"run":1,"list":"/gp_20_07/Datacorn"}],"winner":"524687574992945163"},{"players":[{"id":"107957368997834752","username":"ThatDamnPipsqueak","wins":2,"losses":1,"winner":1,"run":1,"list":"/gp_20_07/ThatDamnPipsqueak"},{"id":"201750307485515776","username":"augur","wins":1,"losses":2,"winner":0,"run":1,"list":"/gp_20_07/augur"}],"winner":"107957368997834752"},{"players":[{"id":"139184614567575553","username":"CanterburyEgg","wins":2,"losses":0,"winner":1,"run":1,"list":"/gp_20_07/CanterburyEgg"},{"id":"197714567537754113","username":"Hoop_Thrower","wins":0,"losses":2,"winner":0,"run":1,"list":"/gp_20_07/Hoop_Thrower"}],"winner":"139184614567575553"},{"players":[{"id":"166685542740787200","username":"FifthDragon","wins":2,"losses":0,"winner":1,"run":1,"list":"/gp_20_07/FifthDragon"},{"id":"154993946525696010","username":"HonchkrowDavid","wins":0,"losses":2,"winner":0,"run":1,"list":"/gp_20_07/HonchkrowDavid"}],"winner":"166685542740787200"},{"players":[{"id":"186824142299856896","username":"kayiu102","wins":2,"losses":1,"winner":1,"run":1,"list":"/gp_20_07/kayiu102"},{"id":"126785105556537344","username":"HerziQuerzi","wins":1,"losses":2,"winner":0,"run":1,"list":"/gp_20_07/HerziQuerzi"}],"winner":"186824142299856896"},{"players":[{"id":"228286499953704961","username":"CyberChronometer","wins":2,"losses":1,"winner":1,"run":1,"list":"/gp_20_07/CyberChronometer"},{"id":"221078603926863872","username":"NazSmith","wins":1,"losses":2,"winner":0,"run":1,"list":"/gp_20_07/NazSmith"}],"winner":"228286499953704961"},{"players":[{"id":"201750307485515776","username":"augur","wins":2,"losses":0,"winner":1,"run":1,"list":"/gp_20_07/augur"},{"id":"180885469037461504","username":"BluesEclipse","wins":0,"losses":2,"winner":0,"run":1,"list":"/gp_20_07/BluesEclipse"}],"winner":"201750307485515776"},{"players":[{"id":"380481522416746502","username":"crushcastles23","wins":2,"losses":0,"winner":1,"run":1,"list":"/gp_20_07/crushcastles23"},{"id":"256060750492073984","username":"Datacorn","wins":0,"losses":2,"winner":0,"run":1,"list":"/gp_20_07/Datacorn"}],"winner":"380481522416746502"},{"players":[{"id":"222555972185358337","username":"TheMafias","wins":2,"losses":0,"winner":1,"run":1,"list":"/gp_20_07/TheMafias"},{"id":"524687574992945163","username":"InfinityChef","wins":0,"losses":2,"winner":0,"run":1,"list":"/gp_20_07/InfinityChef"}],"winner":"222555972185358337"},{"players":[{"id":"221078603926863872","username":"NazSmith","wins":2,"losses":0,"winner":1,"run":1,"list":"/gp_20_07/NazSmith"},{"id":"353148035594977281","username":"gunnarinator","wins":0,"losses":2,"winner":0,"run":1,"list":"/gp_20_07/gunnarinator"}],"winner":"221078603926863872"},{"players":[{"id":"154993946525696010","username":"HonchkrowDavid","wins":2,"losses":1,"winner":1,"run":1,"list":"/gp_20_07/HonchkrowDavid"},{"id":"326956620535955457","username":"Splitmoon","wins":1,"losses":2,"winner":0,"run":1,"list":"/gp_20_07/Splitmoon"}],"winner":"154993946525696010"},{"players":[{"id":"126785105556537344","username":"HerziQuerzi","wins":2,"losses":1,"winner":1,"run":1,"list":"/gp_20_07/HerziQuerzi"},{"id":"460867085694795797","username":"Gateways7","wins":1,"losses":2,"winner":0,"run":1,"list":"/gp_20_07/Gateways7"}],"winner":"126785105556537344"},{"players":[{"id":"197714567537754113","username":"Hoop_Thrower","wins":2,"losses":0,"winner":1,"run":1,"list":"/gp_20_07/Hoop_Thrower"},{"id":"186824142299856896","username":"kayiu102","wins":0,"losses":2,"winner":0,"run":1,"list":"/gp_20_07/kayiu102"}],"winner":"197714567537754113"},{"players":[{"id":"139184614567575553","username":"CanterburyEgg","wins":2,"losses":1,"winner":1,"run":1,"list":"/gp_20_07/CanterburyEgg"},{"id":"228286499953704961","username":"CyberChronometer","wins":1,"losses":2,"winner":0,"run":1,"list":"/gp_20_07/CyberChronometer"}],"winner":"139184614567575553"},{"players":[{"id":"107957368997834752","username":"ThatDamnPipsqueak","wins":2,"losses":1,"winner":1,"run":1,"list":"/gp_20_07/ThatDamnPipsqueak"},{"id":"166685542740787200","username":"FifthDragon","wins":1,"losses":2,"winner":0,"run":1,"list":"/gp_20_07/FifthDragon"}],"winner":"107957368997834752"},{"players":[{"id":"180885469037461504","username":"BluesEclipse","wins":2,"losses":0,"winner":1,"run":0,"list":"/gp_20_07/BluesEclipse"},{"id":"343475440083664896","username":"Bye","wins":0,"losses":2,"winner":0,"run":0,"list":"/gp_20_07/Bye"}],"winner":"180885469037461504"},{"players":[{"id":"353148035594977281","username":"gunnarinator","wins":2,"losses":0,"winner":1,"run":1,"list":"/gp_20_07/gunnarinator"},{"id":"222555972185358337","username":"TheMafias","wins":0,"losses":2,"winner":0,"run":1,"list":"/gp_20_07/TheMafias"}],"winner":"353148035594977281"},{"players":[{"id":"380481522416746502","username":"crushcastles23","wins":2,"losses":0,"winner":1,"run":1,"list":"/gp_20_07/crushcastles23"},{"id":"524687574992945163","username":"InfinityChef","wins":0,"losses":2,"winner":0,"run":1,"list":"/gp_20_07/InfinityChef"}],"winner":"380481522416746502"},{"players":[{"id":"460867085694795797","username":"Gateways7","wins":2,"losses":0,"winner":1,"run":1,"list":"/gp_20_07/Gateways7"},{"id":"201750307485515776","username":"augur","wins":0,"losses":2,"winner":0,"run":1,"list":"/gp_20_07/augur"}],"winner":"460867085694795797"},{"players":[{"id":"197714567537754113","username":"Hoop_Thrower","wins":2,"losses":0,"winner":1,"run":1,"list":"/gp_20_07/Hoop_Thrower"},{"id":"154993946525696010","username":"HonchkrowDavid","wins":0,"losses":2,"winner":0,"run":1,"list":"/gp_20_07/HonchkrowDavid"}],"winner":"197714567537754113"},{"players":[{"id":"126785105556537344","username":"HerziQuerzi","wins":2,"losses":0,"winner":1,"run":1,"list":"/gp_20_07/HerziQuerzi"},{"id":"221078603926863872","username":"NazSmith","wins":0,"losses":2,"winner":0,"run":1,"list":"/gp_20_07/NazSmith"}],"winner":"126785105556537344"},{"players":[{"id":"326956620535955457","username":"Splitmoon","wins":2,"losses":1,"winner":1,"run":1,"list":"/gp_20_07/Splitmoon"},{"id":"228286499953704961","username":"CyberChronometer","wins":1,"losses":2,"winner":0,"run":1,"list":"/gp_20_07/CyberChronometer"}],"winner":"326956620535955457"},{"players":[{"id":"166685542740787200","username":"FifthDragon","wins":2,"losses":1,"winner":1,"run":1,"list":"/gp_20_07/FifthDragon"},{"id":"186824142299856896","username":"kayiu102","wins":1,"losses":2,"winner":0,"run":1,"list":"/gp_20_07/kayiu102"}],"winner":"166685542740787200"},{"players":[{"id":"107957368997834752","username":"ThatDamnPipsqueak","wins":0,"losses":0,"winner":0,"run":1,"list":"/gp_20_07/ThatDamnPipsqueak"},{"id":"139184614567575553","username":"CanterburyEgg","wins":0,"losses":0,"winner":0,"run":1,"list":"/gp_20_07/CanterburyEgg"}],"winner":null},{"players":[{"id":"107957368997834752","username":"ThatDamnPipsqueak","wins":2,"losses":0,"winner":1,"run":0,"list":"/gp_20_07/ThatDamnPipsqueak"},{"id":"343475440083664896","username":"Bye","wins":0,"losses":2,"winner":0,"run":0,"list":"/gp_20_07/Bye"}],"winner":"107957368997834752"},{"players":[{"id":"166685542740787200","username":"FifthDragon","wins":2,"losses":0,"winner":1,"run":1,"list":"/gp_20_07/FifthDragon"},{"id":"197714567537754113","username":"Hoop_Thrower","wins":0,"losses":2,"winner":0,"run":1,"list":"/gp_20_07/Hoop_Thrower"}],"winner":"166685542740787200"},{"players":[{"id":"126785105556537344","username":"HerziQuerzi","wins":2,"losses":0,"winner":1,"run":0,"list":"/gp_20_07/HerziQuerzi"},{"id":"343475440083664896","username":"Bye","wins":0,"losses":2,"winner":0,"run":0,"list":"/gp_20_07/Bye"}],"winner":"126785105556537344"},{"players":[{"id":"139184614567575553","username":"CanterburyEgg","wins":2,"losses":0,"winner":1,"run":0,"list":"/gp_20_07/CanterburyEgg"},{"id":"343475440083664896","username":"Bye","wins":0,"losses":2,"winner":0,"run":0,"list":"/gp_20_07/Bye"}],"winner":"139184614567575553"},{"players":[{"id":"107957368997834752","username":"ThatDamnPipsqueak","wins":2,"losses":0,"winner":1,"run":1,"list":"/gp_20_07/ThatDamnPipsqueak"},{"id":"166685542740787200","username":"FifthDragon","wins":0,"losses":2,"winner":0,"run":1,"list":"/gp_20_07/FifthDragon"}],"winner":"107957368997834752"},{"players":[{"id":"139184614567575553","username":"CanterburyEgg","wins":2,"losses":0,"winner":1,"run":1,"list":"/gp_20_07/CanterburyEgg"},{"id":"126785105556537344","username":"HerziQuerzi","wins":0,"losses":2,"winner":0,"run":1,"list":"/gp_20_07/HerziQuerzi"}],"winner":"139184614567575553"},{"players":[{"id":"139184614567575553","username":"CanterburyEgg","wins":2,"losses":0,"winner":1,"run":1,"list":"/gp_20_07/CanterburyEgg"},{"id":"107957368997834752","username":"ThatDamnPipsqueak","wins":0,"losses":2,"winner":0,"run":1,"list":"/gp_20_07/ThatDamnPipsqueak"}],"winner":"139184614567575553"}],"players":{"180885469037461504":{"username":"BluesEclipse","matches":[[6,11,19,28]],"lists":["/gp_20_07/BluesEclipse"],"opponents":[[["139184614567575553",1],["353148035594977281",1],["201750307485515776",1],["343475440083664896",0]]],"wins":1,"losses":3,"draws":0,"monthScore":1},"126785105556537344":{"username":"HerziQuerzi","matches":[[9,17,24,33,39,42]],"lists":["/gp_20_07/HerziQuerzi"],"opponents":[[["524687574992945163",1],["186824142299856896",1],["460867085694795797",1],["221078603926863872",1],["343475440083664896",0],["139184614567575553",1]]],"wins":4,"losses":2,"draws":0,"monthScore":4},"197714567537754113":{"username":"Hoop_Thrower","matches":[[3,15,25,32,38]],"lists":["/gp_20_07/Hoop_Thrower"],"opponents":[[["353148035594977281",1],["139184614567575553",1],["186824142299856896",1],["154993946525696010",1],["166685542740787200",1]]],"wins":3,"losses":2,"draws":0,"monthScore":3},"107957368997834752":{"username":"ThatDamnPipsqueak","matches":[[8,14,27,36,37,41,43]],"lists":["/gp_20_07/ThatDamnPipsqueak"],"opponents":[[["326956620535955457",1],["201750307485515776",1],["166685542740787200",1],["139184614567575553",1],["343475440083664896",0],["166685542740787200",1],["139184614567575553",1]]],"wins":5,"losses":1,"draws":1,"monthScore":5},"380481522416746502":{"username":"crushcastles23","matches":[[2,12,20,30]],"lists":["/gp_20_07/crushcastles23"],"opponents":[[["166685542740787200",1],["460867085694795797",1],["256060750492073984",1],["524687574992945163",1]]],"wins":2,"losses":2,"draws":0,"monthScore":2},"228286499953704961":{"username":"CyberChronometer","matches":[[7,18,26,34]],"lists":["/gp_20_07/CyberChronometer"],"opponents":[[["460867085694795797",1],["221078603926863872",1],["139184614567575553",1],["326956620535955457",1]]],"wins":2,"losses":2,"draws":0,"monthScore":2},"353148035594977281":{"username":"gunnarinator","matches":[[3,11,22,29]],"lists":["/gp_20_07/gunnarinator"],"opponents":[[["197714567537754113",1],["180885469037461504",1],["221078603926863872",1],["222555972185358337",1]]],"wins":2,"losses":2,"draws":0,"monthScore":2},"221078603926863872":{"username":"NazSmith","matches":[[1,18,22,33]],"lists":["/gp_20_07/NazSmith"],"opponents":[[["222555972185358337",1],["228286499953704961",1],["353148035594977281",1],["126785105556537344",1]]],"wins":2,"losses":2,"draws":0,"monthScore":2},"139184614567575553":{"username":"CanterburyEgg","matches":[[6,15,26,36,40,42,43]],"lists":["/gp_20_07/CanterburyEgg"],"opponents":[[["180885469037461504",1],["197714567537754113",1],["228286499953704961",1],["107957368997834752",1],["343475440083664896",0],["126785105556537344",1],["107957368997834752",1]]],"wins":6,"losses":0,"draws":1,"monthScore":6},"460867085694795797":{"username":"Gateways7","matches":[[7,12,24,31]],"lists":["/gp_20_07/Gateways7"],"opponents":[[["228286499953704961",1],["380481522416746502",1],["126785105556537344",1],["201750307485515776",1]]],"wins":2,"losses":2,"draws":0,"monthScore":2},"524687574992945163":{"username":"InfinityChef","matches":[[9,13,21,30]],"lists":["/gp_20_07/InfinityChef"],"opponents":[[["126785105556537344",1],["256060750492073984",1],["222555972185358337",1],["380481522416746502",1]]],"wins":1,"losses":3,"draws":0,"monthScore":1},"201750307485515776":{"username":"augur","matches":[[5,14,19,31]],"lists":["/gp_20_07/augur"],"opponents":[[["186824142299856896",1],["107957368997834752",1],["180885469037461504",1],["460867085694795797",1]]],"wins":1,"losses":3,"draws":0,"monthScore":1},"256060750492073984":{"username":"Datacorn","matches":[[4,13,20]],"lists":["/gp_20_07/Datacorn"],"opponents":[[["154993946525696010",1],["524687574992945163",1],["380481522416746502",1]]],"wins":0,"losses":3,"draws":0,"monthScore":0},"186824142299856896":{"username":"kayiu102","matches":[[5,17,25,35]],"lists":["/gp_20_07/kayiu102"],"opponents":[[["201750307485515776",1],["126785105556537344",1],["197714567537754113",1],["166685542740787200",1]]],"wins":2,"losses":2,"draws":0,"monthScore":2},"154993946525696010":{"username":"HonchkrowDavid","matches":[[4,16,23,32]],"lists":["/gp_20_07/HonchkrowDavid"],"opponents":[[["256060750492073984",1],["166685542740787200",1],["326956620535955457",1],["197714567537754113",1]]],"wins":2,"losses":2,"draws":0,"monthScore":2},"326956620535955457":{"username":"Splitmoon","matches":[[8,10,23,34]],"lists":["/gp_20_07/Splitmoon"],"opponents":[[["107957368997834752",1],["222555972185358337",1],["154993946525696010",1],["228286499953704961",1]]],"wins":2,"losses":2,"draws":0,"monthScore":2},"222555972185358337":{"username":"TheMafias","matches":[[1,10,21,29]],"lists":["/gp_20_07/TheMafias"],"opponents":[[["221078603926863872",1],["326956620535955457",1],["524687574992945163",1],["353148035594977281",1]]],"wins":1,"losses":3,"draws":0,"monthScore":1},"166685542740787200":{"username":"FifthDragon","matches":[[2,16,27,35,38,41]],"lists":["/gp_20_07/FifthDragon"],"opponents":[[["380481522416746502",1],["154993946525696010",1],["107957368997834752",1],["186824142299856896",1],["197714567537754113",1],["107957368997834752",1]]],"wins":4,"losses":2,"draws":0,"monthScore":4},"343475440083664896":{"username":"Bye","matches":[[28,37,39,40]],"lists":["/gp_20_07/Bye"],"opponents":[[["180885469037461504",0],["107957368997834752",0],["126785105556537344",0],["139184614567575553",0]]],"wins":0,"losses":4,"draws":0,"monthScore":0}}}