{"Herald of Oblivion":{"mainCount":4,"sideCount":0},"Ambitious Necromancer":{"mainCount":3,"sideCount":0},"Guardian of Dusk":{"mainCount":4,"sideCount":0},"Blood Jade Prophet":{"mainCount":4,"sideCount":0},"Wither":{"mainCount":4,"sideCount":0},"Memento Mori":{"mainCount":4,"sideCount":0},"Honorless Offering":{"mainCount":4,"sideCount":0},"Duress":{"mainCount":4,"sideCount":0},"Prying Inquiry":{"mainCount":4,"sideCount":0},"Dark Bargain":{"mainCount":4,"sideCount":0},"Wayfarer's Shrine":{"mainCount":4,"sideCount":0},"Barren Desolation":{"mainCount":1,"sideCount":0},"Flooded Depths":{"mainCount":1,"sideCount":0},"Grim Bastion":{"mainCount":1,"sideCount":0},"Shardstone Rift":{"mainCount":1,"sideCount":0},"Swamp":{"mainCount":13,"sideCount":0},"Chaos in Bloom":{"mainCount":0,"sideCount":4},"Just Business":{"mainCount":0,"sideCount":4},"Shikai's Redoubt":{"mainCount":0,"sideCount":4},"The Afterlife Takes Its Due":{"mainCount":0,"sideCount":3}}